networking_vsphere/__init__.py
networking_vsphere/_i18n.py
networking_vsphere/service.py
networking_vsphere/agent/__init__.py
networking_vsphere/agent/agent.py
networking_vsphere/agent/dvs_neutron_agent.py
networking_vsphere/agent/ovsvapp_agent.py
networking_vsphere/agent/ovsvapp_sg_agent.py
networking_vsphere/agent/etc/neutron/plugins/ml2/ml2_conf_sa.ini
networking_vsphere/agent/firewalls/__init__.py
networking_vsphere/agent/firewalls/dvs_securitygroup_rpc.py
networking_vsphere/agent/firewalls/noop_firewall.py
networking_vsphere/agent/firewalls/vcenter_firewall.py
networking_vsphere/common/__init__.py
networking_vsphere/common/config.py
networking_vsphere/common/constants.py
networking_vsphere/common/dvs_agent_rpc_api.py
networking_vsphere/common/error.py
networking_vsphere/common/exceptions.py
networking_vsphere/common/model.py
networking_vsphere/common/utils.py
networking_vsphere/common/vmware_conf.py
networking_vsphere/db/__init__.py
networking_vsphere/db/ovsvapp_db.py
networking_vsphere/db/ovsvapp_models.py
networking_vsphere/db/migration/__init__.py
networking_vsphere/db/migration/alembic.ini
networking_vsphere/db/migration/cli.py
networking_vsphere/db/migration/alembic_migrations/README
networking_vsphere/db/migration/alembic_migrations/__init__.py
networking_vsphere/db/migration/alembic_migrations/env.py
networking_vsphere/db/migration/alembic_migrations/versions/3f77522fea53_ovsvapp_cluster_vni_allocations.py
networking_vsphere/db/migration/alembic_migrations/versions/4f77522fea53_ovsvapp_clusters.py
networking_vsphere/db/migration/alembic_migrations/versions/HEAD
networking_vsphere/db/migration/alembic_migrations/versions/__init__.py
networking_vsphere/db/migration/alembic_migrations/versions/start_ovsvapp_migration.py
networking_vsphere/drivers/__init__.py
networking_vsphere/drivers/base_manager.py
networking_vsphere/drivers/driver.py
networking_vsphere/drivers/dvs_driver.py
networking_vsphere/drivers/manager.py
networking_vsphere-2.0.0.dist-info/DESCRIPTION.rst
networking_vsphere-2.0.0.dist-info/METADATA
networking_vsphere-2.0.0.dist-info/RECORD
networking_vsphere-2.0.0.dist-info/WHEEL
networking_vsphere-2.0.0.dist-info/entry_points.txt
networking_vsphere-2.0.0.dist-info/metadata.json
networking_vsphere-2.0.0.dist-info/pbr.json
networking_vsphere-2.0.0.dist-info/top_level.txt
